{
  "players" : [ {
    "id" : "player_7636",
    "name" : "Chase Headley",
    "ratings" : {
      "batting" : {
        "vsLeft" : {
          "@type" : "BattingRatings",
          "scale" : {
            "@type" : "OneToOneHundred"
          },
          "contact" : 22,
          "gap" : 26,
          "power" : 18,
          "eye" : 39,
          "k" : 26
        },
        "vsRight" : {
          "@type" : "BattingRatings",
          "scale" : {
            "@type" : "OneToOneHundred"
          },
          "contact" : 25,
          "gap" : 33,
          "power" : 22,
          "eye" : 48,
          "k" : 29
        }
      },
      "defensive" : {
        "positionRating" : {
          "SECOND_BASE" : 0.0,
          "CATCHER" : 0.0,
          "CENTER_FIELD" : 0.0,
          "SHORTSTOP" : 0.0,
          "FIRST_BASE" : 0.0,
          "LEFT_FIELD" : 0.7,
          "THIRD_BASE" : 1.4,
          "RIGHT_FIELD" : 3.0
        },
        "catcher" : {
          "range" : {
            "reference" : 0,
            "present" : true
          },
          "errors" : {
            "reference" : 0,
            "present" : true
          },
          "arm" : {
            "reference" : 0,
            "present" : true
          },
          "dp" : {
            "reference" : 0,
            "present" : true
          },
          "ability" : {
            "reference" : 0,
            "present" : true
          }
        },
        "infield" : {
          "range" : {
            "reference" : 36,
            "present" : true
          },
          "errors" : {
            "reference" : 36,
            "present" : true
          },
          "arm" : {
            "reference" : 36,
            "present" : true
          },
          "dp" : {
            "reference" : 36,
            "present" : true
          },
          "ability" : {
            "reference" : 0,
            "present" : true
          }
        },
        "outfield" : {
          "range" : {
            "reference" : 42,
            "present" : true
          },
          "errors" : {
            "reference" : 41,
            "present" : true
          },
          "arm" : {
            "reference" : 51,
            "present" : true
          },
          "dp" : {
            "reference" : 0,
            "present" : true
          },
          "ability" : {
            "reference" : 0,
            "present" : true
          }
        }
      },
      "pitching" : null,
      "battingPotential" : {
        "scale" : {
          "@type" : "OneToOneHundred"
        },
        "contact" : 67,
        "gap" : 63,
        "power" : 62,
        "eye" : 59,
        "k" : 48
      },
      "pitchingPotential" : null
    },
    "age" : 19,
    "team" : "",
    "salary" : "",
    "battingHand" : "SWITCH",
    "upcomingFreeAgent" : false,
    "injured" : false
  }, {
    "id" : "player_7637",
    "name" : "Craig Hansen",
    "ratings" : {
      "batting" : null,
      "defensive" : {
        "positionRating" : {
          "SECOND_BASE" : 0.0,
          "CATCHER" : 0.0,
          "CENTER_FIELD" : 0.0,
          "SHORTSTOP" : 0.0,
          "FIRST_BASE" : 0.0,
          "LEFT_FIELD" : 0.0,
          "THIRD_BASE" : 0.0,
          "RIGHT_FIELD" : 0.0
        },
        "catcher" : {
          "range" : {
            "reference" : 0,
            "present" : true
          },
          "errors" : {
            "reference" : 0,
            "present" : true
          },
          "arm" : {
            "reference" : 0,
            "present" : true
          },
          "dp" : {
            "reference" : 0,
            "present" : true
          },
          "ability" : {
            "reference" : 0,
            "present" : true
          }
        },
        "infield" : {
          "range" : {
            "reference" : 0,
            "present" : true
          },
          "errors" : {
            "reference" : 0,
            "present" : true
          },
          "arm" : {
            "reference" : 0,
            "present" : true
          },
          "dp" : {
            "reference" : 0,
            "present" : true
          },
          "ability" : {
            "reference" : 0,
            "present" : true
          }
        },
        "outfield" : {
          "range" : {
            "reference" : 0,
            "present" : true
          },
          "errors" : {
            "reference" : 0,
            "present" : true
          },
          "arm" : {
            "reference" : 0,
            "present" : true
          },
          "dp" : {
            "reference" : 0,
            "present" : true
          },
          "ability" : {
            "reference" : 0,
            "present" : true
          }
        }
      },
      "pitching" : {
        "vsLeft" : {
          "@type" : "PitchingRatings",
          "scale" : {
            "@type" : "OneToOneHundred"
          },
          "hits" : 42,
          "gap" : 45,
          "stuff" : 42,
          "control" : 41,
          "movement" : 45,
          "endurance" : 2
        },
        "vsRight" : {
          "@type" : "PitchingRatings",
          "scale" : {
            "@type" : "OneToOneHundred"
          },
          "hits" : 48,
          "gap" : 47,
          "stuff" : 48,
          "control" : 47,
          "movement" : 47,
          "endurance" : 2
        }
      },
      "battingPotential" : null,
      "pitchingPotential" : {
        "scale" : {
          "@type" : "OneToOneHundred"
        },
        "hits" : 47,
        "gap" : 58,
        "stuff" : 47,
        "control" : 51,
        "movement" : 58,
        "endurance" : 2
      }
    },
    "age" : 20,
    "team" : "",
    "salary" : "",
    "battingHand" : "RIGHT",
    "upcomingFreeAgent" : false,
    "injured" : false
  }, {
    "id" : "player_7638",
    "name" : "Alex Gordon",
    "ratings" : {
      "batting" : {
        "vsLeft" : {
          "@type" : "BattingRatings",
          "scale" : {
            "@type" : "OneToOneHundred"
          },
          "contact" : 27,
          "gap" : 40,
          "power" : 24,
          "eye" : 25,
          "k" : 27
        },
        "vsRight" : {
          "@type" : "BattingRatings",
          "scale" : {
            "@type" : "OneToOneHundred"
          },
          "contact" : 30,
          "gap" : 47,
          "power" : 28,
          "eye" : 30,
          "k" : 29
        }
      },
      "defensive" : {
        "positionRating" : {
          "SECOND_BASE" : 0.0,
          "CATCHER" : 0.0,
          "CENTER_FIELD" : 0.0,
          "SHORTSTOP" : 0.2,
          "FIRST_BASE" : 3.3,
          "LEFT_FIELD" : 0.0,
          "THIRD_BASE" : 1.9,
          "RIGHT_FIELD" : 0.0
        },
        "catcher" : {
          "range" : {
            "reference" : 0,
            "present" : true
          },
          "errors" : {
            "reference" : 0,
            "present" : true
          },
          "arm" : {
            "reference" : 0,
            "present" : true
          },
          "dp" : {
            "reference" : 0,
            "present" : true
          },
          "ability" : {
            "reference" : 0,
            "present" : true
          }
        },
        "infield" : {
          "range" : {
            "reference" : 45,
            "present" : true
          },
          "errors" : {
            "reference" : 52,
            "present" : true
          },
          "arm" : {
            "reference" : 52,
            "present" : true
          },
          "dp" : {
            "reference" : 45,
            "present" : true
          },
          "ability" : {
            "reference" : 0,
            "present" : true
          }
        },
        "outfield" : {
          "range" : {
            "reference" : 0,
            "present" : true
          },
          "errors" : {
            "reference" : 0,
            "present" : true
          },
          "arm" : {
            "reference" : 0,
            "present" : true
          },
          "dp" : {
            "reference" : 0,
            "present" : true
          },
          "ability" : {
            "reference" : 0,
            "present" : true
          }
        }
      },
      "pitching" : null,
      "battingPotential" : {
        "scale" : {
          "@type" : "OneToOneHundred"
        },
        "contact" : 63,
        "gap" : 74,
        "power" : 53,
        "eye" : 48,
        "k" : 45
      },
      "pitchingPotential" : null
    },
    "age" : 20,
    "team" : "",
    "salary" : "",
    "battingHand" : "LEFT",
    "upcomingFreeAgent" : false,
    "injured" : false
  }, {
    "id" : "player_7639",
    "name" : "Matt Garza",
    "ratings" : {
      "batting" : null,
      "defensive" : {
        "positionRating" : {
          "SECOND_BASE" : 0.0,
          "CATCHER" : 0.0,
          "CENTER_FIELD" : 0.0,
          "SHORTSTOP" : 0.0,
          "FIRST_BASE" : 0.0,
          "LEFT_FIELD" : 0.0,
          "THIRD_BASE" : 0.0,
          "RIGHT_FIELD" : 0.0
        },
        "catcher" : {
          "range" : {
            "reference" : 0,
            "present" : true
          },
          "errors" : {
            "reference" : 0,
            "present" : true
          },
          "arm" : {
            "reference" : 0,
            "present" : true
          },
          "dp" : {
            "reference" : 0,
            "present" : true
          },
          "ability" : {
            "reference" : 0,
            "present" : true
          }
        },
        "infield" : {
          "range" : {
            "reference" : 0,
            "present" : true
          },
          "errors" : {
            "reference" : 0,
            "present" : true
          },
          "arm" : {
            "reference" : 0,
            "present" : true
          },
          "dp" : {
            "reference" : 0,
            "present" : true
          },
          "ability" : {
            "reference" : 0,
            "present" : true
          }
        },
        "outfield" : {
          "range" : {
            "reference" : 0,
            "present" : true
          },
          "errors" : {
            "reference" : 0,
            "present" : true
          },
          "arm" : {
            "reference" : 0,
            "present" : true
          },
          "dp" : {
            "reference" : 0,
            "present" : true
          },
          "ability" : {
            "reference" : 0,
            "present" : true
          }
        }
      },
      "pitching" : {
        "vsLeft" : {
          "@type" : "PitchingRatings",
          "scale" : {
            "@type" : "OneToOneHundred"
          },
          "hits" : 53,
          "gap" : 54,
          "stuff" : 53,
          "control" : 44,
          "movement" : 54,
          "endurance" : 9
        },
        "vsRight" : {
          "@type" : "PitchingRatings",
          "scale" : {
            "@type" : "OneToOneHundred"
          },
          "hits" : 53,
          "gap" : 54,
          "stuff" : 53,
          "control" : 44,
          "movement" : 54,
          "endurance" : 9
        }
      },
      "battingPotential" : null,
      "pitchingPotential" : {
        "scale" : {
          "@type" : "OneToOneHundred"
        },
        "hits" : 61,
        "gap" : 70,
        "stuff" : 61,
        "control" : 71,
        "movement" : 70,
        "endurance" : 9
      }
    },
    "age" : 20,
    "team" : "",
    "salary" : "",
    "battingHand" : "RIGHT",
    "upcomingFreeAgent" : false,
    "injured" : false
  }, {
    "id" : "player_7644",
    "name" : "Travis Buck",
    "ratings" : {
      "batting" : {
        "vsLeft" : {
          "@type" : "BattingRatings",
          "scale" : {
            "@type" : "OneToOneHundred"
          },
          "contact" : 33,
          "gap" : 48,
          "power" : 23,
          "eye" : 44,
          "k" : 26
        },
        "vsRight" : {
          "@type" : "BattingRatings",
          "scale" : {
            "@type" : "OneToOneHundred"
          },
          "contact" : 38,
          "gap" : 62,
          "power" : 29,
          "eye" : 57,
          "k" : 29
        }
      },
      "defensive" : {
        "positionRating" : {
          "SECOND_BASE" : 0.0,
          "CATCHER" : 0.0,
          "CENTER_FIELD" : 0.0,
          "SHORTSTOP" : 0.0,
          "FIRST_BASE" : 0.0,
          "LEFT_FIELD" : 0.5,
          "THIRD_BASE" : 0.0,
          "RIGHT_FIELD" : 0.5
        },
        "catcher" : {
          "range" : {
            "reference" : 0,
            "present" : true
          },
          "errors" : {
            "reference" : 0,
            "present" : true
          },
          "arm" : {
            "reference" : 0,
            "present" : true
          },
          "dp" : {
            "reference" : 0,
            "present" : true
          },
          "ability" : {
            "reference" : 0,
            "present" : true
          }
        },
        "infield" : {
          "range" : {
            "reference" : 0,
            "present" : true
          },
          "errors" : {
            "reference" : 0,
            "present" : true
          },
          "arm" : {
            "reference" : 0,
            "present" : true
          },
          "dp" : {
            "reference" : 0,
            "present" : true
          },
          "ability" : {
            "reference" : 0,
            "present" : true
          }
        },
        "outfield" : {
          "range" : {
            "reference" : 39,
            "present" : true
          },
          "errors" : {
            "reference" : 40,
            "present" : true
          },
          "arm" : {
            "reference" : 41,
            "present" : true
          },
          "dp" : {
            "reference" : 0,
            "present" : true
          },
          "ability" : {
            "reference" : 0,
            "present" : true
          }
        }
      },
      "pitching" : null,
      "battingPotential" : {
        "scale" : {
          "@type" : "OneToOneHundred"
        },
        "contact" : 69,
        "gap" : 84,
        "power" : 50,
        "eye" : 71,
        "k" : 50
      },
      "pitchingPotential" : null
    },
    "age" : 20,
    "team" : "",
    "salary" : "",
    "battingHand" : "LEFT",
    "upcomingFreeAgent" : false,
    "injured" : false
  }, {
    "id" : "player_7643",
    "name" : "Jeff Clement",
    "ratings" : {
      "batting" : {
        "vsLeft" : {
          "@type" : "BattingRatings",
          "scale" : {
            "@type" : "OneToOneHundred"
          },
          "contact" : 23,
          "gap" : 15,
          "power" : 29,
          "eye" : 29,
          "k" : 25
        },
        "vsRight" : {
          "@type" : "BattingRatings",
          "scale" : {
            "@type" : "OneToOneHundred"
          },
          "contact" : 28,
          "gap" : 21,
          "power" : 40,
          "eye" : 40,
          "k" : 30
        }
      },
      "defensive" : {
        "positionRating" : {
          "SECOND_BASE" : 0.0,
          "CATCHER" : 3.2,
          "CENTER_FIELD" : 0.0,
          "SHORTSTOP" : 0.0,
          "FIRST_BASE" : 0.0,
          "LEFT_FIELD" : 0.0,
          "THIRD_BASE" : 0.0,
          "RIGHT_FIELD" : 0.0
        },
        "catcher" : {
          "range" : {
            "reference" : 0,
            "present" : true
          },
          "errors" : {
            "reference" : 0,
            "present" : true
          },
          "arm" : {
            "reference" : 58,
            "present" : true
          },
          "dp" : {
            "reference" : 0,
            "present" : true
          },
          "ability" : {
            "reference" : 90,
            "present" : true
          }
        },
        "infield" : {
          "range" : {
            "reference" : 0,
            "present" : true
          },
          "errors" : {
            "reference" : 0,
            "present" : true
          },
          "arm" : {
            "reference" : 0,
            "present" : true
          },
          "dp" : {
            "reference" : 0,
            "present" : true
          },
          "ability" : {
            "reference" : 0,
            "present" : true
          }
        },
        "outfield" : {
          "range" : {
            "reference" : 0,
            "present" : true
          },
          "errors" : {
            "reference" : 0,
            "present" : true
          },
          "arm" : {
            "reference" : 0,
            "present" : true
          },
          "dp" : {
            "reference" : 0,
            "present" : true
          },
          "ability" : {
            "reference" : 0,
            "present" : true
          }
        }
      },
      "pitching" : null,
      "battingPotential" : {
        "scale" : {
          "@type" : "OneToOneHundred"
        },
        "contact" : 51,
        "gap" : 43,
        "power" : 55,
        "eye" : 55,
        "k" : 46
      },
      "pitchingPotential" : null
    },
    "age" : 20,
    "team" : "",
    "salary" : "",
    "battingHand" : "LEFT",
    "upcomingFreeAgent" : false,
    "injured" : false
  }, {
    "id" : "player_7646",
    "name" : "Lance Broadway",
    "ratings" : {
      "batting" : null,
      "defensive" : {
        "positionRating" : {
          "SECOND_BASE" : 0.0,
          "CATCHER" : 0.0,
          "CENTER_FIELD" : 0.0,
          "SHORTSTOP" : 0.0,
          "FIRST_BASE" : 0.0,
          "LEFT_FIELD" : 0.0,
          "THIRD_BASE" : 0.0,
          "RIGHT_FIELD" : 0.0
        },
        "catcher" : {
          "range" : {
            "reference" : 0,
            "present" : true
          },
          "errors" : {
            "reference" : 0,
            "present" : true
          },
          "arm" : {
            "reference" : 0,
            "present" : true
          },
          "dp" : {
            "reference" : 0,
            "present" : true
          },
          "ability" : {
            "reference" : 0,
            "present" : true
          }
        },
        "infield" : {
          "range" : {
            "reference" : 0,
            "present" : true
          },
          "errors" : {
            "reference" : 0,
            "present" : true
          },
          "arm" : {
            "reference" : 0,
            "present" : true
          },
          "dp" : {
            "reference" : 0,
            "present" : true
          },
          "ability" : {
            "reference" : 0,
            "present" : true
          }
        },
        "outfield" : {
          "range" : {
            "reference" : 0,
            "present" : true
          },
          "errors" : {
            "reference" : 0,
            "present" : true
          },
          "arm" : {
            "reference" : 0,
            "present" : true
          },
          "dp" : {
            "reference" : 0,
            "present" : true
          },
          "ability" : {
            "reference" : 0,
            "present" : true
          }
        }
      },
      "pitching" : {
        "vsLeft" : {
          "@type" : "PitchingRatings",
          "scale" : {
            "@type" : "OneToOneHundred"
          },
          "hits" : 81,
          "gap" : 75,
          "stuff" : 81,
          "control" : 25,
          "movement" : 75,
          "endurance" : 2
        },
        "vsRight" : {
          "@type" : "PitchingRatings",
          "scale" : {
            "@type" : "OneToOneHundred"
          },
          "hits" : 79,
          "gap" : 75,
          "stuff" : 79,
          "control" : 24,
          "movement" : 75,
          "endurance" : 2
        }
      },
      "battingPotential" : null,
      "pitchingPotential" : {
        "scale" : {
          "@type" : "OneToOneHundred"
        },
        "hits" : 80,
        "gap" : 83,
        "stuff" : 80,
        "control" : 37,
        "movement" : 83,
        "endurance" : 2
      }
    },
    "age" : 20,
    "team" : "",
    "salary" : "",
    "battingHand" : "RIGHT",
    "upcomingFreeAgent" : false,
    "injured" : false
  }, {
    "id" : "player_7645",
    "name" : "Clay Buchholz",
    "ratings" : {
      "batting" : null,
      "defensive" : {
        "positionRating" : {
          "SECOND_BASE" : 0.0,
          "CATCHER" : 0.0,
          "CENTER_FIELD" : 0.0,
          "SHORTSTOP" : 0.0,
          "FIRST_BASE" : 0.0,
          "LEFT_FIELD" : 0.0,
          "THIRD_BASE" : 0.0,
          "RIGHT_FIELD" : 0.0
        },
        "catcher" : {
          "range" : {
            "reference" : 0,
            "present" : true
          },
          "errors" : {
            "reference" : 0,
            "present" : true
          },
          "arm" : {
            "reference" : 0,
            "present" : true
          },
          "dp" : {
            "reference" : 0,
            "present" : true
          },
          "ability" : {
            "reference" : 0,
            "present" : true
          }
        },
        "infield" : {
          "range" : {
            "reference" : 0,
            "present" : true
          },
          "errors" : {
            "reference" : 0,
            "present" : true
          },
          "arm" : {
            "reference" : 0,
            "present" : true
          },
          "dp" : {
            "reference" : 0,
            "present" : true
          },
          "ability" : {
            "reference" : 0,
            "present" : true
          }
        },
        "outfield" : {
          "range" : {
            "reference" : 0,
            "present" : true
          },
          "errors" : {
            "reference" : 0,
            "present" : true
          },
          "arm" : {
            "reference" : 0,
            "present" : true
          },
          "dp" : {
            "reference" : 0,
            "present" : true
          },
          "ability" : {
            "reference" : 0,
            "present" : true
          }
        }
      },
      "pitching" : {
        "vsLeft" : {
          "@type" : "PitchingRatings",
          "scale" : {
            "@type" : "OneToOneHundred"
          },
          "hits" : 20,
          "gap" : 41,
          "stuff" : 20,
          "control" : 40,
          "movement" : 41,
          "endurance" : 7
        },
        "vsRight" : {
          "@type" : "PitchingRatings",
          "scale" : {
            "@type" : "OneToOneHundred"
          },
          "hits" : 20,
          "gap" : 41,
          "stuff" : 20,
          "control" : 42,
          "movement" : 41,
          "endurance" : 7
        }
      },
      "battingPotential" : null,
      "pitchingPotential" : {
        "scale" : {
          "@type" : "OneToOneHundred"
        },
        "hits" : 68,
        "gap" : 65,
        "stuff" : 68,
        "control" : 51,
        "movement" : 65,
        "endurance" : 7
      }
    },
    "age" : 19,
    "team" : "",
    "salary" : "",
    "battingHand" : "LEFT",
    "upcomingFreeAgent" : false,
    "injured" : false
  }, {
    "id" : "player_7640",
    "name" : "Yunel Escobar",
    "ratings" : {
      "batting" : {
        "vsLeft" : {
          "@type" : "BattingRatings",
          "scale" : {
            "@type" : "OneToOneHundred"
          },
          "contact" : 43,
          "gap" : 46,
          "power" : 15,
          "eye" : 34,
          "k" : 48
        },
        "vsRight" : {
          "@type" : "BattingRatings",
          "scale" : {
            "@type" : "OneToOneHundred"
          },
          "contact" : 40,
          "gap" : 41,
          "power" : 14,
          "eye" : 30,
          "k" : 46
        }
      },
      "defensive" : {
        "positionRating" : {
          "SECOND_BASE" : 0.3,
          "CATCHER" : 0.0,
          "CENTER_FIELD" : 0.0,
          "SHORTSTOP" : 1.2,
          "FIRST_BASE" : 0.0,
          "LEFT_FIELD" : 0.0,
          "THIRD_BASE" : 0.3,
          "RIGHT_FIELD" : 0.0
        },
        "catcher" : {
          "range" : {
            "reference" : 0,
            "present" : true
          },
          "errors" : {
            "reference" : 0,
            "present" : true
          },
          "arm" : {
            "reference" : 0,
            "present" : true
          },
          "dp" : {
            "reference" : 0,
            "present" : true
          },
          "ability" : {
            "reference" : 0,
            "present" : true
          }
        },
        "infield" : {
          "range" : {
            "reference" : 50,
            "present" : true
          },
          "errors" : {
            "reference" : 48,
            "present" : true
          },
          "arm" : {
            "reference" : 48,
            "present" : true
          },
          "dp" : {
            "reference" : 47,
            "present" : true
          },
          "ability" : {
            "reference" : 0,
            "present" : true
          }
        },
        "outfield" : {
          "range" : {
            "reference" : 0,
            "present" : true
          },
          "errors" : {
            "reference" : 0,
            "present" : true
          },
          "arm" : {
            "reference" : 0,
            "present" : true
          },
          "dp" : {
            "reference" : 0,
            "present" : true
          },
          "ability" : {
            "reference" : 0,
            "present" : true
          }
        }
      },
      "pitching" : null,
      "battingPotential" : {
        "scale" : {
          "@type" : "OneToOneHundred"
        },
        "contact" : 69,
        "gap" : 50,
        "power" : 37,
        "eye" : 61,
        "k" : 77
      },
      "pitchingPotential" : null
    },
    "age" : 21,
    "team" : "",
    "salary" : "",
    "battingHand" : "RIGHT",
    "upcomingFreeAgent" : false,
    "injured" : false
  }, {
    "id" : "player_7642",
    "name" : "Joey Devine",
    "ratings" : {
      "batting" : null,
      "defensive" : {
        "positionRating" : {
          "SECOND_BASE" : 0.0,
          "CATCHER" : 0.0,
          "CENTER_FIELD" : 0.0,
          "SHORTSTOP" : 0.0,
          "FIRST_BASE" : 0.0,
          "LEFT_FIELD" : 0.0,
          "THIRD_BASE" : 0.0,
          "RIGHT_FIELD" : 0.0
        },
        "catcher" : {
          "range" : {
            "reference" : 0,
            "present" : true
          },
          "errors" : {
            "reference" : 0,
            "present" : true
          },
          "arm" : {
            "reference" : 0,
            "present" : true
          },
          "dp" : {
            "reference" : 0,
            "present" : true
          },
          "ability" : {
            "reference" : 0,
            "present" : true
          }
        },
        "infield" : {
          "range" : {
            "reference" : 0,
            "present" : true
          },
          "errors" : {
            "reference" : 0,
            "present" : true
          },
          "arm" : {
            "reference" : 0,
            "present" : true
          },
          "dp" : {
            "reference" : 0,
            "present" : true
          },
          "ability" : {
            "reference" : 0,
            "present" : true
          }
        },
        "outfield" : {
          "range" : {
            "reference" : 0,
            "present" : true
          },
          "errors" : {
            "reference" : 0,
            "present" : true
          },
          "arm" : {
            "reference" : 0,
            "present" : true
          },
          "dp" : {
            "reference" : 0,
            "present" : true
          },
          "ability" : {
            "reference" : 0,
            "present" : true
          }
        }
      },
      "pitching" : {
        "vsLeft" : {
          "@type" : "PitchingRatings",
          "scale" : {
            "@type" : "OneToOneHundred"
          },
          "hits" : 50,
          "gap" : 39,
          "stuff" : 50,
          "control" : 33,
          "movement" : 39,
          "endurance" : 2
        },
        "vsRight" : {
          "@type" : "PitchingRatings",
          "scale" : {
            "@type" : "OneToOneHundred"
          },
          "hits" : 55,
          "gap" : 39,
          "stuff" : 55,
          "control" : 36,
          "movement" : 39,
          "endurance" : 2
        }
      },
      "battingPotential" : null,
      "pitchingPotential" : {
        "scale" : {
          "@type" : "OneToOneHundred"
        },
        "hits" : 77,
        "gap" : 71,
        "stuff" : 77,
        "control" : 63,
        "movement" : 71,
        "endurance" : 2
      }
    },
    "age" : 20,
    "team" : "",
    "salary" : "",
    "battingHand" : "RIGHT",
    "upcomingFreeAgent" : false,
    "injured" : false
  }, {
    "id" : "player_7641",
    "name" : "Jacoby Ellsbury",
    "ratings" : {
      "batting" : {
        "vsLeft" : {
          "@type" : "BattingRatings",
          "scale" : {
            "@type" : "OneToOneHundred"
          },
          "contact" : 31,
          "gap" : 30,
          "power" : 22,
          "eye" : 30,
          "k" : 45
        },
        "vsRight" : {
          "@type" : "BattingRatings",
          "scale" : {
            "@type" : "OneToOneHundred"
          },
          "contact" : 32,
          "gap" : 31,
          "power" : 24,
          "eye" : 31,
          "k" : 46
        }
      },
      "defensive" : {
        "positionRating" : {
          "SECOND_BASE" : 0.0,
          "CATCHER" : 0.0,
          "CENTER_FIELD" : 0.0,
          "SHORTSTOP" : 0.0,
          "FIRST_BASE" : 0.0,
          "LEFT_FIELD" : 0.6,
          "THIRD_BASE" : 0.0,
          "RIGHT_FIELD" : 0.5
        },
        "catcher" : {
          "range" : {
            "reference" : 0,
            "present" : true
          },
          "errors" : {
            "reference" : 0,
            "present" : true
          },
          "arm" : {
            "reference" : 0,
            "present" : true
          },
          "dp" : {
            "reference" : 0,
            "present" : true
          },
          "ability" : {
            "reference" : 0,
            "present" : true
          }
        },
        "infield" : {
          "range" : {
            "reference" : 0,
            "present" : true
          },
          "errors" : {
            "reference" : 0,
            "present" : true
          },
          "arm" : {
            "reference" : 0,
            "present" : true
          },
          "dp" : {
            "reference" : 0,
            "present" : true
          },
          "ability" : {
            "reference" : 0,
            "present" : true
          }
        },
        "outfield" : {
          "range" : {
            "reference" : 42,
            "present" : true
          },
          "errors" : {
            "reference" : 42,
            "present" : true
          },
          "arm" : {
            "reference" : 42,
            "present" : true
          },
          "dp" : {
            "reference" : 0,
            "present" : true
          },
          "ability" : {
            "reference" : 0,
            "present" : true
          }
        }
      },
      "pitching" : null,
      "battingPotential" : {
        "scale" : {
          "@type" : "OneToOneHundred"
        },
        "contact" : 66,
        "gap" : 65,
        "power" : 54,
        "eye" : 65,
        "k" : 65
      },
      "pitchingPotential" : null
    },
    "age" : 20,
    "team" : "",
    "salary" : "",
    "battingHand" : "LEFT",
    "upcomingFreeAgent" : false,
    "injured" : false
  }, {
    "id" : "player_7623",
    "name" : "Troy Tulowitzki",
    "ratings" : {
      "batting" : {
        "vsLeft" : {
          "@type" : "BattingRatings",
          "scale" : {
            "@type" : "OneToOneHundred"
          },
          "contact" : 42,
          "gap" : 37,
          "power" : 41,
          "eye" : 41,
          "k" : 31
        },
        "vsRight" : {
          "@type" : "BattingRatings",
          "scale" : {
            "@type" : "OneToOneHundred"
          },
          "contact" : 39,
          "gap" : 33,
          "power" : 37,
          "eye" : 37,
          "k" : 29
        }
      },
      "defensive" : {
        "positionRating" : {
          "SECOND_BASE" : 0.0,
          "CATCHER" : 0.0,
          "CENTER_FIELD" : 0.0,
          "SHORTSTOP" : 1.5,
          "FIRST_BASE" : 0.0,
          "LEFT_FIELD" : 0.0,
          "THIRD_BASE" : 0.0,
          "RIGHT_FIELD" : 0.0
        },
        "catcher" : {
          "range" : {
            "reference" : 0,
            "present" : true
          },
          "errors" : {
            "reference" : 0,
            "present" : true
          },
          "arm" : {
            "reference" : 0,
            "present" : true
          },
          "dp" : {
            "reference" : 0,
            "present" : true
          },
          "ability" : {
            "reference" : 0,
            "present" : true
          }
        },
        "infield" : {
          "range" : {
            "reference" : 53,
            "present" : true
          },
          "errors" : {
            "reference" : 49,
            "present" : true
          },
          "arm" : {
            "reference" : 50,
            "present" : true
          },
          "dp" : {
            "reference" : 49,
            "present" : true
          },
          "ability" : {
            "reference" : 0,
            "present" : true
          }
        },
        "outfield" : {
          "range" : {
            "reference" : 0,
            "present" : true
          },
          "errors" : {
            "reference" : 0,
            "present" : true
          },
          "arm" : {
            "reference" : 0,
            "present" : true
          },
          "dp" : {
            "reference" : 0,
            "present" : true
          },
          "ability" : {
            "reference" : 0,
            "present" : true
          }
        }
      },
      "pitching" : null,
      "battingPotential" : {
        "scale" : {
          "@type" : "OneToOneHundred"
        },
        "contact" : 73,
        "gap" : 66,
        "power" : 65,
        "eye" : 57,
        "k" : 52
      },
      "pitchingPotential" : null
    },
    "age" : 19,
    "team" : "",
    "salary" : "",
    "battingHand" : "RIGHT",
    "upcomingFreeAgent" : false,
    "injured" : false
  }, {
    "id" : "player_7624",
    "name" : "Joe Thatcher",
    "ratings" : {
      "batting" : null,
      "defensive" : {
        "positionRating" : {
          "SECOND_BASE" : 0.0,
          "CATCHER" : 0.0,
          "CENTER_FIELD" : 0.0,
          "SHORTSTOP" : 0.0,
          "FIRST_BASE" : 0.0,
          "LEFT_FIELD" : 0.0,
          "THIRD_BASE" : 0.0,
          "RIGHT_FIELD" : 0.0
        },
        "catcher" : {
          "range" : {
            "reference" : 0,
            "present" : true
          },
          "errors" : {
            "reference" : 0,
            "present" : true
          },
          "arm" : {
            "reference" : 0,
            "present" : true
          },
          "dp" : {
            "reference" : 0,
            "present" : true
          },
          "ability" : {
            "reference" : 0,
            "present" : true
          }
        },
        "infield" : {
          "range" : {
            "reference" : 0,
            "present" : true
          },
          "errors" : {
            "reference" : 0,
            "present" : true
          },
          "arm" : {
            "reference" : 0,
            "present" : true
          },
          "dp" : {
            "reference" : 0,
            "present" : true
          },
          "ability" : {
            "reference" : 0,
            "present" : true
          }
        },
        "outfield" : {
          "range" : {
            "reference" : 0,
            "present" : true
          },
          "errors" : {
            "reference" : 0,
            "present" : true
          },
          "arm" : {
            "reference" : 0,
            "present" : true
          },
          "dp" : {
            "reference" : 0,
            "present" : true
          },
          "ability" : {
            "reference" : 0,
            "present" : true
          }
        }
      },
      "pitching" : {
        "vsLeft" : {
          "@type" : "PitchingRatings",
          "scale" : {
            "@type" : "OneToOneHundred"
          },
          "hits" : 35,
          "gap" : 72,
          "stuff" : 35,
          "control" : 60,
          "movement" : 72,
          "endurance" : 2
        },
        "vsRight" : {
          "@type" : "PitchingRatings",
          "scale" : {
            "@type" : "OneToOneHundred"
          },
          "hits" : 33,
          "gap" : 70,
          "stuff" : 33,
          "control" : 57,
          "movement" : 70,
          "endurance" : 2
        }
      },
      "battingPotential" : null,
      "pitchingPotential" : {
        "scale" : {
          "@type" : "OneToOneHundred"
        },
        "hits" : 36,
        "gap" : 72,
        "stuff" : 36,
        "control" : 61,
        "movement" : 72,
        "endurance" : 2
      }
    },
    "age" : 22,
    "team" : "",
    "salary" : "",
    "battingHand" : "LEFT",
    "upcomingFreeAgent" : false,
    "injured" : false
  }, {
    "id" : "player_7621",
    "name" : "Mike Zagurski",
    "ratings" : {
      "batting" : null,
      "defensive" : {
        "positionRating" : {
          "SECOND_BASE" : 0.0,
          "CATCHER" : 0.0,
          "CENTER_FIELD" : 0.0,
          "SHORTSTOP" : 0.0,
          "FIRST_BASE" : 0.0,
          "LEFT_FIELD" : 0.0,
          "THIRD_BASE" : 0.0,
          "RIGHT_FIELD" : 0.0
        },
        "catcher" : {
          "range" : {
            "reference" : 0,
            "present" : true
          },
          "errors" : {
            "reference" : 0,
            "present" : true
          },
          "arm" : {
            "reference" : 0,
            "present" : true
          },
          "dp" : {
            "reference" : 0,
            "present" : true
          },
          "ability" : {
            "reference" : 0,
            "present" : true
          }
        },
        "infield" : {
          "range" : {
            "reference" : 0,
            "present" : true
          },
          "errors" : {
            "reference" : 0,
            "present" : true
          },
          "arm" : {
            "reference" : 0,
            "present" : true
          },
          "dp" : {
            "reference" : 0,
            "present" : true
          },
          "ability" : {
            "reference" : 0,
            "present" : true
          }
        },
        "outfield" : {
          "range" : {
            "reference" : 0,
            "present" : true
          },
          "errors" : {
            "reference" : 0,
            "present" : true
          },
          "arm" : {
            "reference" : 0,
            "present" : true
          },
          "dp" : {
            "reference" : 0,
            "present" : true
          },
          "ability" : {
            "reference" : 0,
            "present" : true
          }
        }
      },
      "pitching" : {
        "vsLeft" : {
          "@type" : "PitchingRatings",
          "scale" : {
            "@type" : "OneToOneHundred"
          },
          "hits" : 38,
          "gap" : 40,
          "stuff" : 38,
          "control" : 38,
          "movement" : 40,
          "endurance" : 2
        },
        "vsRight" : {
          "@type" : "PitchingRatings",
          "scale" : {
            "@type" : "OneToOneHundred"
          },
          "hits" : 36,
          "gap" : 39,
          "stuff" : 36,
          "control" : 35,
          "movement" : 39,
          "endurance" : 2
        }
      },
      "battingPotential" : null,
      "pitchingPotential" : {
        "scale" : {
          "@type" : "OneToOneHundred"
        },
        "hits" : 48,
        "gap" : 50,
        "stuff" : 48,
        "control" : 61,
        "movement" : 50,
        "endurance" : 2
      }
    },
    "age" : 21,
    "team" : "",
    "salary" : "",
    "battingHand" : "LEFT",
    "upcomingFreeAgent" : false,
    "injured" : false
  }, {
    "id" : "player_7622",
    "name" : "Justin Upton",
    "ratings" : {
      "batting" : {
        "vsLeft" : {
          "@type" : "BattingRatings",
          "scale" : {
            "@type" : "OneToOneHundred"
          },
          "contact" : 24,
          "gap" : 46,
          "power" : 18,
          "eye" : 25,
          "k" : 28
        },
        "vsRight" : {
          "@type" : "BattingRatings",
          "scale" : {
            "@type" : "OneToOneHundred"
          },
          "contact" : 22,
          "gap" : 41,
          "power" : 16,
          "eye" : 22,
          "k" : 27
        }
      },
      "defensive" : {
        "positionRating" : {
          "SECOND_BASE" : 0.0,
          "CATCHER" : 0.0,
          "CENTER_FIELD" : 0.0,
          "SHORTSTOP" : 0.0,
          "FIRST_BASE" : 0.0,
          "LEFT_FIELD" : 0.6,
          "THIRD_BASE" : 0.0,
          "RIGHT_FIELD" : 0.5
        },
        "catcher" : {
          "range" : {
            "reference" : 0,
            "present" : true
          },
          "errors" : {
            "reference" : 0,
            "present" : true
          },
          "arm" : {
            "reference" : 0,
            "present" : true
          },
          "dp" : {
            "reference" : 0,
            "present" : true
          },
          "ability" : {
            "reference" : 0,
            "present" : true
          }
        },
        "infield" : {
          "range" : {
            "reference" : 0,
            "present" : true
          },
          "errors" : {
            "reference" : 0,
            "present" : true
          },
          "arm" : {
            "reference" : 0,
            "present" : true
          },
          "dp" : {
            "reference" : 0,
            "present" : true
          },
          "ability" : {
            "reference" : 0,
            "present" : true
          }
        },
        "outfield" : {
          "range" : {
            "reference" : 38,
            "present" : true
          },
          "errors" : {
            "reference" : 38,
            "present" : true
          },
          "arm" : {
            "reference" : 41,
            "present" : true
          },
          "dp" : {
            "reference" : 0,
            "present" : true
          },
          "ability" : {
            "reference" : 0,
            "present" : true
          }
        }
      },
      "pitching" : null,
      "battingPotential" : {
        "scale" : {
          "@type" : "OneToOneHundred"
        },
        "contact" : 65,
        "gap" : 64,
        "power" : 67,
        "eye" : 54,
        "k" : 52
      },
      "pitchingPotential" : null
    },
    "age" : 16,
    "team" : "",
    "salary" : "",
    "battingHand" : "RIGHT",
    "upcomingFreeAgent" : false,
    "injured" : false
  }, {
    "id" : "player_7620",
    "name" : "Ryan Zimmerman",
    "ratings" : {
      "batting" : {
        "vsLeft" : {
          "@type" : "BattingRatings",
          "scale" : {
            "@type" : "OneToOneHundred"
          },
          "contact" : 41,
          "gap" : 61,
          "power" : 31,
          "eye" : 30,
          "k" : 26
        },
        "vsRight" : {
          "@type" : "BattingRatings",
          "scale" : {
            "@type" : "OneToOneHundred"
          },
          "contact" : 39,
          "gap" : 52,
          "power" : 25,
          "eye" : 24,
          "k" : 23
        }
      },
      "defensive" : {
        "positionRating" : {
          "SECOND_BASE" : 0.0,
          "CATCHER" : 0.0,
          "CENTER_FIELD" : 0.0,
          "SHORTSTOP" : 0.2,
          "FIRST_BASE" : 0.0,
          "LEFT_FIELD" : 0.0,
          "THIRD_BASE" : 2.4,
          "RIGHT_FIELD" : 0.0
        },
        "catcher" : {
          "range" : {
            "reference" : 0,
            "present" : true
          },
          "errors" : {
            "reference" : 0,
            "present" : true
          },
          "arm" : {
            "reference" : 0,
            "present" : true
          },
          "dp" : {
            "reference" : 0,
            "present" : true
          },
          "ability" : {
            "reference" : 0,
            "present" : true
          }
        },
        "infield" : {
          "range" : {
            "reference" : 47,
            "present" : true
          },
          "errors" : {
            "reference" : 55,
            "present" : true
          },
          "arm" : {
            "reference" : 55,
            "present" : true
          },
          "dp" : {
            "reference" : 47,
            "present" : true
          },
          "ability" : {
            "reference" : 0,
            "present" : true
          }
        },
        "outfield" : {
          "range" : {
            "reference" : 0,
            "present" : true
          },
          "errors" : {
            "reference" : 0,
            "present" : true
          },
          "arm" : {
            "reference" : 0,
            "present" : true
          },
          "dp" : {
            "reference" : 0,
            "present" : true
          },
          "ability" : {
            "reference" : 0,
            "present" : true
          }
        }
      },
      "pitching" : null,
      "battingPotential" : {
        "scale" : {
          "@type" : "OneToOneHundred"
        },
        "contact" : 78,
        "gap" : 82,
        "power" : 63,
        "eye" : 59,
        "k" : 58
      },
      "pitchingPotential" : null
    },
    "age" : 19,
    "team" : "",
    "salary" : "",
    "battingHand" : "RIGHT",
    "upcomingFreeAgent" : false,
    "injured" : false
  }, {
    "id" : "player_7647",
    "name" : "Ryan J Braun",
    "ratings" : {
      "batting" : {
        "vsLeft" : {
          "@type" : "BattingRatings",
          "scale" : {
            "@type" : "OneToOneHundred"
          },
          "contact" : 45,
          "gap" : 47,
          "power" : 66,
          "eye" : 27,
          "k" : 29
        },
        "vsRight" : {
          "@type" : "BattingRatings",
          "scale" : {
            "@type" : "OneToOneHundred"
          },
          "contact" : 38,
          "gap" : 38,
          "power" : 53,
          "eye" : 22,
          "k" : 26
        }
      },
      "defensive" : {
        "positionRating" : {
          "SECOND_BASE" : 0.0,
          "CATCHER" : 0.0,
          "CENTER_FIELD" : 0.0,
          "SHORTSTOP" : 0.0,
          "FIRST_BASE" : 0.0,
          "LEFT_FIELD" : 0.8,
          "THIRD_BASE" : 1.4,
          "RIGHT_FIELD" : 3.1
        },
        "catcher" : {
          "range" : {
            "reference" : 0,
            "present" : true
          },
          "errors" : {
            "reference" : 0,
            "present" : true
          },
          "arm" : {
            "reference" : 0,
            "present" : true
          },
          "dp" : {
            "reference" : 0,
            "present" : true
          },
          "ability" : {
            "reference" : 0,
            "present" : true
          }
        },
        "infield" : {
          "range" : {
            "reference" : 36,
            "present" : true
          },
          "errors" : {
            "reference" : 36,
            "present" : true
          },
          "arm" : {
            "reference" : 36,
            "present" : true
          },
          "dp" : {
            "reference" : 36,
            "present" : true
          },
          "ability" : {
            "reference" : 0,
            "present" : true
          }
        },
        "outfield" : {
          "range" : {
            "reference" : 43,
            "present" : true
          },
          "errors" : {
            "reference" : 44,
            "present" : true
          },
          "arm" : {
            "reference" : 53,
            "present" : true
          },
          "dp" : {
            "reference" : 0,
            "present" : true
          },
          "ability" : {
            "reference" : 0,
            "present" : true
          }
        }
      },
      "pitching" : null,
      "battingPotential" : {
        "scale" : {
          "@type" : "OneToOneHundred"
        },
        "contact" : 81,
        "gap" : 78,
        "power" : 86,
        "eye" : 52,
        "k" : 60
      },
      "pitchingPotential" : null
    },
    "age" : 20,
    "team" : "",
    "salary" : "",
    "battingHand" : "RIGHT",
    "upcomingFreeAgent" : false,
    "injured" : false
  }, {
    "id" : "player_7629",
    "name" : "Garrett Olson",
    "ratings" : {
      "batting" : null,
      "defensive" : {
        "positionRating" : {
          "SECOND_BASE" : 0.0,
          "CATCHER" : 0.0,
          "CENTER_FIELD" : 0.0,
          "SHORTSTOP" : 0.0,
          "FIRST_BASE" : 0.0,
          "LEFT_FIELD" : 0.0,
          "THIRD_BASE" : 0.0,
          "RIGHT_FIELD" : 0.0
        },
        "catcher" : {
          "range" : {
            "reference" : 0,
            "present" : true
          },
          "errors" : {
            "reference" : 0,
            "present" : true
          },
          "arm" : {
            "reference" : 0,
            "present" : true
          },
          "dp" : {
            "reference" : 0,
            "present" : true
          },
          "ability" : {
            "reference" : 0,
            "present" : true
          }
        },
        "infield" : {
          "range" : {
            "reference" : 0,
            "present" : true
          },
          "errors" : {
            "reference" : 0,
            "present" : true
          },
          "arm" : {
            "reference" : 0,
            "present" : true
          },
          "dp" : {
            "reference" : 0,
            "present" : true
          },
          "ability" : {
            "reference" : 0,
            "present" : true
          }
        },
        "outfield" : {
          "range" : {
            "reference" : 0,
            "present" : true
          },
          "errors" : {
            "reference" : 0,
            "present" : true
          },
          "arm" : {
            "reference" : 0,
            "present" : true
          },
          "dp" : {
            "reference" : 0,
            "present" : true
          },
          "ability" : {
            "reference" : 0,
            "present" : true
          }
        }
      },
      "pitching" : {
        "vsLeft" : {
          "@type" : "PitchingRatings",
          "scale" : {
            "@type" : "OneToOneHundred"
          },
          "hits" : 50,
          "gap" : 47,
          "stuff" : 50,
          "control" : 44,
          "movement" : 47,
          "endurance" : 8
        },
        "vsRight" : {
          "@type" : "PitchingRatings",
          "scale" : {
            "@type" : "OneToOneHundred"
          },
          "hits" : 50,
          "gap" : 47,
          "stuff" : 50,
          "control" : 44,
          "movement" : 47,
          "endurance" : 8
        }
      },
      "battingPotential" : null,
      "pitchingPotential" : {
        "scale" : {
          "@type" : "OneToOneHundred"
        },
        "hits" : 50,
        "gap" : 63,
        "stuff" : 50,
        "control" : 47,
        "movement" : 63,
        "endurance" : 8
      }
    },
    "age" : 20,
    "team" : "",
    "salary" : "",
    "battingHand" : "RIGHT",
    "upcomingFreeAgent" : false,
    "injured" : false
  }, {
    "id" : "player_7648",
    "name" : "Yuniesky Betancourt",
    "ratings" : {
      "batting" : {
        "vsLeft" : {
          "@type" : "BattingRatings",
          "scale" : {
            "@type" : "OneToOneHundred"
          },
          "contact" : 54,
          "gap" : 57,
          "power" : 20,
          "eye" : 21,
          "k" : 76
        },
        "vsRight" : {
          "@type" : "BattingRatings",
          "scale" : {
            "@type" : "OneToOneHundred"
          },
          "contact" : 51,
          "gap" : 54,
          "power" : 19,
          "eye" : 20,
          "k" : 74
        }
      },
      "defensive" : {
        "positionRating" : {
          "SECOND_BASE" : 0.3,
          "CATCHER" : 0.0,
          "CENTER_FIELD" : 0.0,
          "SHORTSTOP" : 2.2,
          "FIRST_BASE" : 0.0,
          "LEFT_FIELD" : 0.0,
          "THIRD_BASE" : 0.0,
          "RIGHT_FIELD" : 0.0
        },
        "catcher" : {
          "range" : {
            "reference" : 0,
            "present" : true
          },
          "errors" : {
            "reference" : 0,
            "present" : true
          },
          "arm" : {
            "reference" : 0,
            "present" : true
          },
          "dp" : {
            "reference" : 0,
            "present" : true
          },
          "ability" : {
            "reference" : 0,
            "present" : true
          }
        },
        "infield" : {
          "range" : {
            "reference" : 58,
            "present" : true
          },
          "errors" : {
            "reference" : 54,
            "present" : true
          },
          "arm" : {
            "reference" : 54,
            "present" : true
          },
          "dp" : {
            "reference" : 54,
            "present" : true
          },
          "ability" : {
            "reference" : 0,
            "present" : true
          }
        },
        "outfield" : {
          "range" : {
            "reference" : 0,
            "present" : true
          },
          "errors" : {
            "reference" : 0,
            "present" : true
          },
          "arm" : {
            "reference" : 0,
            "present" : true
          },
          "dp" : {
            "reference" : 0,
            "present" : true
          },
          "ability" : {
            "reference" : 0,
            "present" : true
          }
        }
      },
      "pitching" : null,
      "battingPotential" : {
        "scale" : {
          "@type" : "OneToOneHundred"
        },
        "contact" : 68,
        "gap" : 65,
        "power" : 31,
        "eye" : 45,
        "k" : 86
      },
      "pitchingPotential" : null
    },
    "age" : 22,
    "team" : "",
    "salary" : "",
    "battingHand" : "RIGHT",
    "upcomingFreeAgent" : false,
    "injured" : false
  }, {
    "id" : "player_7627",
    "name" : "Steven Pearce",
    "ratings" : {
      "batting" : {
        "vsLeft" : {
          "@type" : "BattingRatings",
          "scale" : {
            "@type" : "OneToOneHundred"
          },
          "contact" : 29,
          "gap" : 42,
          "power" : 19,
          "eye" : 35,
          "k" : 29
        },
        "vsRight" : {
          "@type" : "BattingRatings",
          "scale" : {
            "@type" : "OneToOneHundred"
          },
          "contact" : 27,
          "gap" : 35,
          "power" : 16,
          "eye" : 29,
          "k" : 26
        }
      },
      "defensive" : {
        "positionRating" : {
          "SECOND_BASE" : 0.0,
          "CATCHER" : 0.0,
          "CENTER_FIELD" : 0.0,
          "SHORTSTOP" : 0.0,
          "FIRST_BASE" : 0.4,
          "LEFT_FIELD" : 0.5,
          "THIRD_BASE" : 0.0,
          "RIGHT_FIELD" : 0.4
        },
        "catcher" : {
          "range" : {
            "reference" : 0,
            "present" : true
          },
          "errors" : {
            "reference" : 0,
            "present" : true
          },
          "arm" : {
            "reference" : 0,
            "present" : true
          },
          "dp" : {
            "reference" : 0,
            "present" : true
          },
          "ability" : {
            "reference" : 0,
            "present" : true
          }
        },
        "infield" : {
          "range" : {
            "reference" : 36,
            "present" : true
          },
          "errors" : {
            "reference" : 36,
            "present" : true
          },
          "arm" : {
            "reference" : 36,
            "present" : true
          },
          "dp" : {
            "reference" : 36,
            "present" : true
          },
          "ability" : {
            "reference" : 0,
            "present" : true
          }
        },
        "outfield" : {
          "range" : {
            "reference" : 37,
            "present" : true
          },
          "errors" : {
            "reference" : 37,
            "present" : true
          },
          "arm" : {
            "reference" : 38,
            "present" : true
          },
          "dp" : {
            "reference" : 0,
            "present" : true
          },
          "ability" : {
            "reference" : 0,
            "present" : true
          }
        }
      },
      "pitching" : null,
      "battingPotential" : {
        "scale" : {
          "@type" : "OneToOneHundred"
        },
        "contact" : 51,
        "gap" : 62,
        "power" : 41,
        "eye" : 50,
        "k" : 46
      },
      "pitchingPotential" : null
    },
    "age" : 20,
    "team" : "",
    "salary" : "",
    "battingHand" : "RIGHT",
    "upcomingFreeAgent" : false,
    "injured" : false
  }, {
    "id" : "player_7628",
    "name" : "Micah Owings",
    "ratings" : {
      "batting" : null,
      "defensive" : {
        "positionRating" : {
          "SECOND_BASE" : 0.0,
          "CATCHER" : 0.0,
          "CENTER_FIELD" : 0.0,
          "SHORTSTOP" : 0.0,
          "FIRST_BASE" : 0.0,
          "LEFT_FIELD" : 0.0,
          "THIRD_BASE" : 0.0,
          "RIGHT_FIELD" : 0.0
        },
        "catcher" : {
          "range" : {
            "reference" : 0,
            "present" : true
          },
          "errors" : {
            "reference" : 0,
            "present" : true
          },
          "arm" : {
            "reference" : 0,
            "present" : true
          },
          "dp" : {
            "reference" : 0,
            "present" : true
          },
          "ability" : {
            "reference" : 0,
            "present" : true
          }
        },
        "infield" : {
          "range" : {
            "reference" : 0,
            "present" : true
          },
          "errors" : {
            "reference" : 0,
            "present" : true
          },
          "arm" : {
            "reference" : 0,
            "present" : true
          },
          "dp" : {
            "reference" : 0,
            "present" : true
          },
          "ability" : {
            "reference" : 0,
            "present" : true
          }
        },
        "outfield" : {
          "range" : {
            "reference" : 0,
            "present" : true
          },
          "errors" : {
            "reference" : 0,
            "present" : true
          },
          "arm" : {
            "reference" : 0,
            "present" : true
          },
          "dp" : {
            "reference" : 0,
            "present" : true
          },
          "ability" : {
            "reference" : 0,
            "present" : true
          }
        }
      },
      "pitching" : {
        "vsLeft" : {
          "@type" : "PitchingRatings",
          "scale" : {
            "@type" : "OneToOneHundred"
          },
          "hits" : 36,
          "gap" : 37,
          "stuff" : 36,
          "control" : 44,
          "movement" : 37,
          "endurance" : 9
        },
        "vsRight" : {
          "@type" : "PitchingRatings",
          "scale" : {
            "@type" : "OneToOneHundred"
          },
          "hits" : 38,
          "gap" : 37,
          "stuff" : 38,
          "control" : 47,
          "movement" : 37,
          "endurance" : 9
        }
      },
      "battingPotential" : null,
      "pitchingPotential" : {
        "scale" : {
          "@type" : "OneToOneHundred"
        },
        "hits" : 58,
        "gap" : 60,
        "stuff" : 58,
        "control" : 68,
        "movement" : 60,
        "endurance" : 9
      }
    },
    "age" : 21,
    "team" : "",
    "salary" : "",
    "battingHand" : "RIGHT",
    "upcomingFreeAgent" : false,
    "injured" : false
  }, {
    "id" : "player_7625",
    "name" : "Kevin Slowey",
    "ratings" : {
      "batting" : null,
      "defensive" : {
        "positionRating" : {
          "SECOND_BASE" : 0.0,
          "CATCHER" : 0.0,
          "CENTER_FIELD" : 0.0,
          "SHORTSTOP" : 0.0,
          "FIRST_BASE" : 0.0,
          "LEFT_FIELD" : 0.0,
          "THIRD_BASE" : 0.0,
          "RIGHT_FIELD" : 0.0
        },
        "catcher" : {
          "range" : {
            "reference" : 0,
            "present" : true
          },
          "errors" : {
            "reference" : 0,
            "present" : true
          },
          "arm" : {
            "reference" : 0,
            "present" : true
          },
          "dp" : {
            "reference" : 0,
            "present" : true
          },
          "ability" : {
            "reference" : 0,
            "present" : true
          }
        },
        "infield" : {
          "range" : {
            "reference" : 0,
            "present" : true
          },
          "errors" : {
            "reference" : 0,
            "present" : true
          },
          "arm" : {
            "reference" : 0,
            "present" : true
          },
          "dp" : {
            "reference" : 0,
            "present" : true
          },
          "ability" : {
            "reference" : 0,
            "present" : true
          }
        },
        "outfield" : {
          "range" : {
            "reference" : 0,
            "present" : true
          },
          "errors" : {
            "reference" : 0,
            "present" : true
          },
          "arm" : {
            "reference" : 0,
            "present" : true
          },
          "dp" : {
            "reference" : 0,
            "present" : true
          },
          "ability" : {
            "reference" : 0,
            "present" : true
          }
        }
      },
      "pitching" : {
        "vsLeft" : {
          "@type" : "PitchingRatings",
          "scale" : {
            "@type" : "OneToOneHundred"
          },
          "hits" : 17,
          "gap" : 35,
          "stuff" : 17,
          "control" : 35,
          "movement" : 35,
          "endurance" : 1
        },
        "vsRight" : {
          "@type" : "PitchingRatings",
          "scale" : {
            "@type" : "OneToOneHundred"
          },
          "hits" : 19,
          "gap" : 36,
          "stuff" : 19,
          "control" : 40,
          "movement" : 36,
          "endurance" : 1
        }
      },
      "battingPotential" : null,
      "pitchingPotential" : {
        "scale" : {
          "@type" : "OneToOneHundred"
        },
        "hits" : 57,
        "gap" : 53,
        "stuff" : 57,
        "control" : 88,
        "movement" : 53,
        "endurance" : 1
      }
    },
    "age" : 19,
    "team" : "",
    "salary" : "",
    "battingHand" : "RIGHT",
    "upcomingFreeAgent" : false,
    "injured" : false
  }, {
    "id" : "player_7626",
    "name" : "Mike Pelfrey",
    "ratings" : {
      "batting" : null,
      "defensive" : {
        "positionRating" : {
          "SECOND_BASE" : 0.0,
          "CATCHER" : 0.0,
          "CENTER_FIELD" : 0.0,
          "SHORTSTOP" : 0.0,
          "FIRST_BASE" : 0.0,
          "LEFT_FIELD" : 0.0,
          "THIRD_BASE" : 0.0,
          "RIGHT_FIELD" : 0.0
        },
        "catcher" : {
          "range" : {
            "reference" : 0,
            "present" : true
          },
          "errors" : {
            "reference" : 0,
            "present" : true
          },
          "arm" : {
            "reference" : 0,
            "present" : true
          },
          "dp" : {
            "reference" : 0,
            "present" : true
          },
          "ability" : {
            "reference" : 0,
            "present" : true
          }
        },
        "infield" : {
          "range" : {
            "reference" : 0,
            "present" : true
          },
          "errors" : {
            "reference" : 0,
            "present" : true
          },
          "arm" : {
            "reference" : 0,
            "present" : true
          },
          "dp" : {
            "reference" : 0,
            "present" : true
          },
          "ability" : {
            "reference" : 0,
            "present" : true
          }
        },
        "outfield" : {
          "range" : {
            "reference" : 0,
            "present" : true
          },
          "errors" : {
            "reference" : 0,
            "present" : true
          },
          "arm" : {
            "reference" : 0,
            "present" : true
          },
          "dp" : {
            "reference" : 0,
            "present" : true
          },
          "ability" : {
            "reference" : 0,
            "present" : true
          }
        }
      },
      "pitching" : {
        "vsLeft" : {
          "@type" : "PitchingRatings",
          "scale" : {
            "@type" : "OneToOneHundred"
          },
          "hits" : 48,
          "gap" : 61,
          "stuff" : 48,
          "control" : 42,
          "movement" : 61,
          "endurance" : 8
        },
        "vsRight" : {
          "@type" : "PitchingRatings",
          "scale" : {
            "@type" : "OneToOneHundred"
          },
          "hits" : 51,
          "gap" : 63,
          "stuff" : 51,
          "control" : 45,
          "movement" : 63,
          "endurance" : 8
        }
      },
      "battingPotential" : null,
      "pitchingPotential" : {
        "scale" : {
          "@type" : "OneToOneHundred"
        },
        "hits" : 53,
        "gap" : 84,
        "stuff" : 53,
        "control" : 75,
        "movement" : 84,
        "endurance" : 8
      }
    },
    "age" : 20,
    "team" : "",
    "salary" : "",
    "battingHand" : "RIGHT",
    "upcomingFreeAgent" : false,
    "injured" : false
  }, {
    "id" : "player_7635",
    "name" : "John Lannan",
    "ratings" : {
      "batting" : null,
      "defensive" : {
        "positionRating" : {
          "SECOND_BASE" : 0.0,
          "CATCHER" : 0.0,
          "CENTER_FIELD" : 0.0,
          "SHORTSTOP" : 0.0,
          "FIRST_BASE" : 0.0,
          "LEFT_FIELD" : 0.0,
          "THIRD_BASE" : 0.0,
          "RIGHT_FIELD" : 0.0
        },
        "catcher" : {
          "range" : {
            "reference" : 0,
            "present" : true
          },
          "errors" : {
            "reference" : 0,
            "present" : true
          },
          "arm" : {
            "reference" : 0,
            "present" : true
          },
          "dp" : {
            "reference" : 0,
            "present" : true
          },
          "ability" : {
            "reference" : 0,
            "present" : true
          }
        },
        "infield" : {
          "range" : {
            "reference" : 0,
            "present" : true
          },
          "errors" : {
            "reference" : 0,
            "present" : true
          },
          "arm" : {
            "reference" : 0,
            "present" : true
          },
          "dp" : {
            "reference" : 0,
            "present" : true
          },
          "ability" : {
            "reference" : 0,
            "present" : true
          }
        },
        "outfield" : {
          "range" : {
            "reference" : 0,
            "present" : true
          },
          "errors" : {
            "reference" : 0,
            "present" : true
          },
          "arm" : {
            "reference" : 0,
            "present" : true
          },
          "dp" : {
            "reference" : 0,
            "present" : true
          },
          "ability" : {
            "reference" : 0,
            "present" : true
          }
        }
      },
      "pitching" : {
        "vsLeft" : {
          "@type" : "PitchingRatings",
          "scale" : {
            "@type" : "OneToOneHundred"
          },
          "hits" : 49,
          "gap" : 59,
          "stuff" : 49,
          "control" : 45,
          "movement" : 59,
          "endurance" : 9
        },
        "vsRight" : {
          "@type" : "PitchingRatings",
          "scale" : {
            "@type" : "OneToOneHundred"
          },
          "hits" : 50,
          "gap" : 59,
          "stuff" : 50,
          "control" : 45,
          "movement" : 59,
          "endurance" : 9
        }
      },
      "battingPotential" : null,
      "pitchingPotential" : {
        "scale" : {
          "@type" : "OneToOneHundred"
        },
        "hits" : 56,
        "gap" : 62,
        "stuff" : 56,
        "control" : 59,
        "movement" : 62,
        "endurance" : 9
      }
    },
    "age" : 19,
    "team" : "",
    "salary" : "",
    "battingHand" : "LEFT",
    "upcomingFreeAgent" : false,
    "injured" : false
  }, {
    "id" : "player_7634",
    "name" : "Jensen Lewis",
    "ratings" : {
      "batting" : null,
      "defensive" : {
        "positionRating" : {
          "SECOND_BASE" : 0.0,
          "CATCHER" : 0.0,
          "CENTER_FIELD" : 0.0,
          "SHORTSTOP" : 0.0,
          "FIRST_BASE" : 0.0,
          "LEFT_FIELD" : 0.0,
          "THIRD_BASE" : 0.0,
          "RIGHT_FIELD" : 0.0
        },
        "catcher" : {
          "range" : {
            "reference" : 0,
            "present" : true
          },
          "errors" : {
            "reference" : 0,
            "present" : true
          },
          "arm" : {
            "reference" : 0,
            "present" : true
          },
          "dp" : {
            "reference" : 0,
            "present" : true
          },
          "ability" : {
            "reference" : 0,
            "present" : true
          }
        },
        "infield" : {
          "range" : {
            "reference" : 0,
            "present" : true
          },
          "errors" : {
            "reference" : 0,
            "present" : true
          },
          "arm" : {
            "reference" : 0,
            "present" : true
          },
          "dp" : {
            "reference" : 0,
            "present" : true
          },
          "ability" : {
            "reference" : 0,
            "present" : true
          }
        },
        "outfield" : {
          "range" : {
            "reference" : 0,
            "present" : true
          },
          "errors" : {
            "reference" : 0,
            "present" : true
          },
          "arm" : {
            "reference" : 0,
            "present" : true
          },
          "dp" : {
            "reference" : 0,
            "present" : true
          },
          "ability" : {
            "reference" : 0,
            "present" : true
          }
        }
      },
      "pitching" : {
        "vsLeft" : {
          "@type" : "PitchingRatings",
          "scale" : {
            "@type" : "OneToOneHundred"
          },
          "hits" : 44,
          "gap" : 56,
          "stuff" : 44,
          "control" : 41,
          "movement" : 56,
          "endurance" : 2
        },
        "vsRight" : {
          "@type" : "PitchingRatings",
          "scale" : {
            "@type" : "OneToOneHundred"
          },
          "hits" : 49,
          "gap" : 59,
          "stuff" : 49,
          "control" : 46,
          "movement" : 59,
          "endurance" : 2
        }
      },
      "battingPotential" : null,
      "pitchingPotential" : {
        "scale" : {
          "@type" : "OneToOneHundred"
        },
        "hits" : 48,
        "gap" : 68,
        "stuff" : 48,
        "control" : 50,
        "movement" : 68,
        "endurance" : 2
      }
    },
    "age" : 19,
    "team" : "",
    "salary" : "",
    "battingHand" : "RIGHT",
    "upcomingFreeAgent" : false,
    "injured" : false
  }, {
    "id" : "player_7633",
    "name" : "Justin Maxwell",
    "ratings" : {
      "batting" : {
        "vsLeft" : {
          "@type" : "BattingRatings",
          "scale" : {
            "@type" : "OneToOneHundred"
          },
          "contact" : 20,
          "gap" : 24,
          "power" : 36,
          "eye" : 39,
          "k" : 28
        },
        "vsRight" : {
          "@type" : "BattingRatings",
          "scale" : {
            "@type" : "OneToOneHundred"
          },
          "contact" : 18,
          "gap" : 21,
          "power" : 32,
          "eye" : 35,
          "k" : 27
        }
      },
      "defensive" : {
        "positionRating" : {
          "SECOND_BASE" : 0.0,
          "CATCHER" : 0.0,
          "CENTER_FIELD" : 0.0,
          "SHORTSTOP" : 0.0,
          "FIRST_BASE" : 0.0,
          "LEFT_FIELD" : 0.5,
          "THIRD_BASE" : 0.0,
          "RIGHT_FIELD" : 2.3
        },
        "catcher" : {
          "range" : {
            "reference" : 0,
            "present" : true
          },
          "errors" : {
            "reference" : 0,
            "present" : true
          },
          "arm" : {
            "reference" : 0,
            "present" : true
          },
          "dp" : {
            "reference" : 0,
            "present" : true
          },
          "ability" : {
            "reference" : 0,
            "present" : true
          }
        },
        "infield" : {
          "range" : {
            "reference" : 0,
            "present" : true
          },
          "errors" : {
            "reference" : 0,
            "present" : true
          },
          "arm" : {
            "reference" : 0,
            "present" : true
          },
          "dp" : {
            "reference" : 0,
            "present" : true
          },
          "ability" : {
            "reference" : 0,
            "present" : true
          }
        },
        "outfield" : {
          "range" : {
            "reference" : 42,
            "present" : true
          },
          "errors" : {
            "reference" : 40,
            "present" : true
          },
          "arm" : {
            "reference" : 48,
            "present" : true
          },
          "dp" : {
            "reference" : 0,
            "present" : true
          },
          "ability" : {
            "reference" : 0,
            "present" : true
          }
        }
      },
      "pitching" : null,
      "battingPotential" : {
        "scale" : {
          "@type" : "OneToOneHundred"
        },
        "contact" : 23,
        "gap" : 26,
        "power" : 43,
        "eye" : 43,
        "k" : 31
      },
      "pitchingPotential" : null
    },
    "age" : 20,
    "team" : "",
    "salary" : "",
    "battingHand" : "RIGHT",
    "upcomingFreeAgent" : false,
    "injured" : false
  }, {
    "id" : "player_7632",
    "name" : "Cameron Maybin",
    "ratings" : {
      "batting" : {
        "vsLeft" : {
          "@type" : "BattingRatings",
          "scale" : {
            "@type" : "OneToOneHundred"
          },
          "contact" : 18,
          "gap" : 31,
          "power" : 24,
          "eye" : 36,
          "k" : 28
        },
        "vsRight" : {
          "@type" : "BattingRatings",
          "scale" : {
            "@type" : "OneToOneHundred"
          },
          "contact" : 16,
          "gap" : 27,
          "power" : 21,
          "eye" : 32,
          "k" : 27
        }
      },
      "defensive" : {
        "positionRating" : {
          "SECOND_BASE" : 0.0,
          "CATCHER" : 0.0,
          "CENTER_FIELD" : 0.0,
          "SHORTSTOP" : 0.0,
          "FIRST_BASE" : 0.0,
          "LEFT_FIELD" : 0.5,
          "THIRD_BASE" : 0.0,
          "RIGHT_FIELD" : 0.4
        },
        "catcher" : {
          "range" : {
            "reference" : 0,
            "present" : true
          },
          "errors" : {
            "reference" : 0,
            "present" : true
          },
          "arm" : {
            "reference" : 0,
            "present" : true
          },
          "dp" : {
            "reference" : 0,
            "present" : true
          },
          "ability" : {
            "reference" : 0,
            "present" : true
          }
        },
        "infield" : {
          "range" : {
            "reference" : 0,
            "present" : true
          },
          "errors" : {
            "reference" : 0,
            "present" : true
          },
          "arm" : {
            "reference" : 0,
            "present" : true
          },
          "dp" : {
            "reference" : 0,
            "present" : true
          },
          "ability" : {
            "reference" : 0,
            "present" : true
          }
        },
        "outfield" : {
          "range" : {
            "reference" : 39,
            "present" : true
          },
          "errors" : {
            "reference" : 38,
            "present" : true
          },
          "arm" : {
            "reference" : 38,
            "present" : true
          },
          "dp" : {
            "reference" : 0,
            "present" : true
          },
          "ability" : {
            "reference" : 0,
            "present" : true
          }
        }
      },
      "pitching" : null,
      "battingPotential" : {
        "scale" : {
          "@type" : "OneToOneHundred"
        },
        "contact" : 55,
        "gap" : 53,
        "power" : 64,
        "eye" : 60,
        "k" : 44
      },
      "pitchingPotential" : null
    },
    "age" : 16,
    "team" : "",
    "salary" : "",
    "battingHand" : "RIGHT",
    "upcomingFreeAgent" : false,
    "injured" : false
  }, {
    "id" : "player_7631",
    "name" : "Jonathan Meloan",
    "ratings" : {
      "batting" : null,
      "defensive" : {
        "positionRating" : {
          "SECOND_BASE" : 0.0,
          "CATCHER" : 0.0,
          "CENTER_FIELD" : 0.0,
          "SHORTSTOP" : 0.0,
          "FIRST_BASE" : 0.0,
          "LEFT_FIELD" : 0.0,
          "THIRD_BASE" : 0.0,
          "RIGHT_FIELD" : 0.0
        },
        "catcher" : {
          "range" : {
            "reference" : 0,
            "present" : true
          },
          "errors" : {
            "reference" : 0,
            "present" : true
          },
          "arm" : {
            "reference" : 0,
            "present" : true
          },
          "dp" : {
            "reference" : 0,
            "present" : true
          },
          "ability" : {
            "reference" : 0,
            "present" : true
          }
        },
        "infield" : {
          "range" : {
            "reference" : 0,
            "present" : true
          },
          "errors" : {
            "reference" : 0,
            "present" : true
          },
          "arm" : {
            "reference" : 0,
            "present" : true
          },
          "dp" : {
            "reference" : 0,
            "present" : true
          },
          "ability" : {
            "reference" : 0,
            "present" : true
          }
        },
        "outfield" : {
          "range" : {
            "reference" : 0,
            "present" : true
          },
          "errors" : {
            "reference" : 0,
            "present" : true
          },
          "arm" : {
            "reference" : 0,
            "present" : true
          },
          "dp" : {
            "reference" : 0,
            "present" : true
          },
          "ability" : {
            "reference" : 0,
            "present" : true
          }
        }
      },
      "pitching" : {
        "vsLeft" : {
          "@type" : "PitchingRatings",
          "scale" : {
            "@type" : "OneToOneHundred"
          },
          "hits" : 35,
          "gap" : 36,
          "stuff" : 35,
          "control" : 1,
          "movement" : 36,
          "endurance" : 2
        },
        "vsRight" : {
          "@type" : "PitchingRatings",
          "scale" : {
            "@type" : "OneToOneHundred"
          },
          "hits" : 36,
          "gap" : 36,
          "stuff" : 36,
          "control" : 1,
          "movement" : 36,
          "endurance" : 2
        }
      },
      "battingPotential" : null,
      "pitchingPotential" : {
        "scale" : {
          "@type" : "OneToOneHundred"
        },
        "hits" : 45,
        "gap" : 48,
        "stuff" : 45,
        "control" : 1,
        "movement" : 48,
        "endurance" : 2
      }
    },
    "age" : 19,
    "team" : "",
    "salary" : "",
    "battingHand" : "RIGHT",
    "upcomingFreeAgent" : false,
    "injured" : false
  }, {
    "id" : "player_7630",
    "name" : "Kendry Morales",
    "ratings" : {
      "batting" : {
        "vsLeft" : {
          "@type" : "BattingRatings",
          "scale" : {
            "@type" : "OneToOneHundred"
          },
          "contact" : 38,
          "gap" : 49,
          "power" : 37,
          "eye" : 37,
          "k" : 51
        },
        "vsRight" : {
          "@type" : "BattingRatings",
          "scale" : {
            "@type" : "OneToOneHundred"
          },
          "contact" : 33,
          "gap" : 40,
          "power" : 31,
          "eye" : 31,
          "k" : 46
        }
      },
      "defensive" : {
        "positionRating" : {
          "SECOND_BASE" : 0.0,
          "CATCHER" : 0.0,
          "CENTER_FIELD" : 0.0,
          "SHORTSTOP" : 0.0,
          "FIRST_BASE" : 3.0,
          "LEFT_FIELD" : 2.0,
          "THIRD_BASE" : 0.0,
          "RIGHT_FIELD" : 1.7
        },
        "catcher" : {
          "range" : {
            "reference" : 0,
            "present" : true
          },
          "errors" : {
            "reference" : 0,
            "present" : true
          },
          "arm" : {
            "reference" : 0,
            "present" : true
          },
          "dp" : {
            "reference" : 0,
            "present" : true
          },
          "ability" : {
            "reference" : 0,
            "present" : true
          }
        },
        "infield" : {
          "range" : {
            "reference" : 48,
            "present" : true
          },
          "errors" : {
            "reference" : 66,
            "present" : true
          },
          "arm" : {
            "reference" : 48,
            "present" : true
          },
          "dp" : {
            "reference" : 48,
            "present" : true
          },
          "ability" : {
            "reference" : 0,
            "present" : true
          }
        },
        "outfield" : {
          "range" : {
            "reference" : 80,
            "present" : true
          },
          "errors" : {
            "reference" : 36,
            "present" : true
          },
          "arm" : {
            "reference" : 36,
            "present" : true
          },
          "dp" : {
            "reference" : 0,
            "present" : true
          },
          "ability" : {
            "reference" : 0,
            "present" : true
          }
        }
      },
      "pitching" : null,
      "battingPotential" : {
        "scale" : {
          "@type" : "OneToOneHundred"
        },
        "contact" : 62,
        "gap" : 57,
        "power" : 53,
        "eye" : 43,
        "k" : 59
      },
      "pitchingPotential" : null
    },
    "age" : 20,
    "team" : "",
    "salary" : "",
    "battingHand" : "SWITCH",
    "upcomingFreeAgent" : false,
    "injured" : false
  } ]
}